[
{
    "model": "chatapp.message",
    "pk": 1,
    "fields": {
        "chat": 2,
        "author": 2,
        "content": "Ut tempus sollicitudin velit id volutpat.",
        "timestamp": "2024-01-02T20:01:48.538Z"
    }
},
{
    "model": "chatapp.message",
    "pk": 2,
    "fields": {
        "chat": 2,
        "author": 6,
        "content": "Vivamus nec auctor risus.",
        "timestamp": "2024-01-02T20:02:05.714Z"
    }
},
{
    "model": "chatapp.message",
    "pk": 3,
    "fields": {
        "chat": 2,
        "author": 2,
        "content": "Sed sed elit ut nisi auctor lobortis et at metus. Fusce mattis orci libero, non placerat nisi efficitur sit amet. Integer scelerisque eros eu sollicitudin vehicula. Morbi maximus vulputate lectus, ac tincidunt augue tempor vel. Interdum et malesuada fames ac ante ipsum primis in faucibus.",
        "timestamp": "2024-01-02T20:02:22.651Z"
    }
},
{
    "model": "chatapp.message",
    "pk": 4,
    "fields": {
        "chat": 2,
        "author": 2,
        "content": "Fusce malesuada tempor lectus ut consectetur. Donec molestie consequat suscipit. Quisque non nisl id metus pellentesque facilisis ut nec nunc. In risus risus, fermentum non viverra id, egestas sit amet ex. Phasellus luctus urna sem, eu facilisis ipsum dapibus nec.",
        "timestamp": "2024-01-02T20:05:09.918Z"
    }
},
{
    "model": "chatapp.message",
    "pk": 5,
    "fields": {
        "chat": 2,
        "author": 6,
        "content": "Nulla nec elit id ipsum bibendum blandit et non purus. Etiam augue sem, cursus eget suscipit ac, feugiat at elit. Fusce sed massa ut est pulvinar laoreet non eu enim. Pellentesque laoreet vestibulum sem eget bibendum. Aliquam id mauris non quam vehicula eleifend sed congue sem. Suspendisse sit amet justo ut ipsum congue varius in pretium nibh. Integer non bibendum dolor.",
        "timestamp": "2024-01-02T20:06:30.237Z"
    }
},
{
    "model": "chatapp.message",
    "pk": 6,
    "fields": {
        "chat": 2,
        "author": 6,
        "content": "Sed fringilla velit in dui pharetra commodo eu vel est. Suspendisse dignissim pharetra mi, vel venenatis erat tincidunt a.",
        "timestamp": "2024-01-02T20:06:49.957Z"
    }
},
{
    "model": "chatapp.message",
    "pk": 7,
    "fields": {
        "chat": 2,
        "author": 6,
        "content": "Donec id elit elementum, suscipit sem a, aliquam enim.",
        "timestamp": "2024-01-02T20:07:12.139Z"
    }
},
{
    "model": "chatapp.message",
    "pk": 8,
    "fields": {
        "chat": 2,
        "author": 2,
        "content": "Suspendisse commodo.",
        "timestamp": "2024-01-02T20:08:29.189Z"
    }
},
{
    "model": "chatapp.message",
    "pk": 9,
    "fields": {
        "chat": 2,
        "author": 6,
        "content": "Morbi vulputate ultricies orci, vel maximus turpis fermentum ut. Donec ut dignissim mi. Nunc eleifend tristique tortor, in pulvinar justo tempus quis. In hac habitasse platea dictumst. Sed eleifend in tortor a egestas.",
        "timestamp": "2024-01-02T20:09:04.988Z"
    }
},
{
    "model": "chatapp.message",
    "pk": 10,
    "fields": {
        "chat": 2,
        "author": 6,
        "content": "Vivamus in turpis in eros elementum maximus. Nullam facilisis faucibus augue, id sodales ante laoreet eu. Cras eu dapibus nisl, et ultrices neque.",
        "timestamp": "2024-01-02T20:09:19.296Z"
    }
},
{
    "model": "chatapp.message",
    "pk": 11,
    "fields": {
        "chat": 2,
        "author": 2,
        "content": "Aliquam vitae accumsan arcu. Nulla et metus id ligula aliquam fringilla. Sed tortor tellus, consequat id ornare tincidunt, malesuada sit amet nisl.",
        "timestamp": "2024-01-02T20:09:34.714Z"
    }
},
{
    "model": "chatapp.message",
    "pk": 12,
    "fields": {
        "chat": 2,
        "author": 6,
        "content": "Class aptent taciti sociosqu ad litora torquent per conubia nostra, per inceptos himenaeos.",
        "timestamp": "2024-01-06T07:09:19.296Z"
    }
},
{
    "model": "chatapp.message",
    "pk": 13,
    "fields": {
        "chat": 2,
        "author": 2,
        "content": "Duis semper hendrerit euismod.",
        "timestamp": "2024-01-06T09:09:34.714Z"
    }
},
{
    "model": "chatapp.message",
    "pk": 14,
    "fields": {
        "chat": 2,
        "author": 6,
        "content": "Vivamus volutpat malesuada sem, nec laoreet magna. Donec id erat tincidunt, euismod est malesuada, pellentesque nisi.",
        "timestamp": "2024-01-06T10:19:19.296Z"
    }
},
{
    "model": "chatapp.message",
    "pk": 15,
    "fields": {
        "chat": 2,
        "author": 2,
        "content": "Fusce luctus sodales pharetra.",
        "timestamp": "2024-01-06T10:20:34.714Z"
    }
},
{
    "model": "chatapp.message",
    "pk": 16,
    "fields": {
        "chat": 3,
        "author": 3,
        "content": "Ut tempus sollicitudin velit id volutpat.",
        "timestamp": "2024-01-02T20:01:48.538Z"
    }
},
{
    "model": "chatapp.message",
    "pk": 17,
    "fields": {
        "chat": 3,
        "author": 8,
        "content": "Vivamus nec auctor risus.",
        "timestamp": "2024-01-02T20:02:05.714Z"
    }
},
{
    "model": "chatapp.message",
    "pk": 18,
    "fields": {
        "chat": 3,
        "author": 3,
        "content": "Sed sed elit ut nisi auctor lobortis et at metus. Fusce mattis orci libero, non placerat nisi efficitur sit amet. Integer scelerisque eros eu sollicitudin vehicula. Morbi maximus vulputate lectus, ac tincidunt augue tempor vel. Interdum et malesuada fames ac ante ipsum primis in faucibus.",
        "timestamp": "2024-01-02T20:02:22.651Z"
    }
},
{
    "model": "chatapp.message",
    "pk": 19,
    "fields": {
        "chat": 3,
        "author": 3,
        "content": "Fusce malesuada tempor lectus ut consectetur. Donec molestie consequat suscipit. Quisque non nisl id metus pellentesque facilisis ut nec nunc. In risus risus, fermentum non viverra id, egestas sit amet ex. Phasellus luctus urna sem, eu facilisis ipsum dapibus nec.",
        "timestamp": "2024-01-02T20:05:09.918Z"
    }
},
{
    "model": "chatapp.message",
    "pk": 20,
    "fields": {
        "chat": 3,
        "author": 8,
        "content": "Nulla nec elit id ipsum bibendum blandit et non purus. Etiam augue sem, cursus eget suscipit ac, feugiat at elit. Fusce sed massa ut est pulvinar laoreet non eu enim. Pellentesque laoreet vestibulum sem eget bibendum. Aliquam id mauris non quam vehicula eleifend sed congue sem. Suspendisse sit amet justo ut ipsum congue varius in pretium nibh. Integer non bibendum dolor.",
        "timestamp": "2024-01-02T20:06:30.237Z"
    }
},
{
    "model": "chatapp.message",
    "pk": 21,
    "fields": {
        "chat": 3,
        "author": 8,
        "content": "Sed fringilla velit in dui pharetra commodo eu vel est. Suspendisse dignissim pharetra mi, vel venenatis erat tincidunt a.",
        "timestamp": "2024-01-02T20:06:49.957Z"
    }
},
{
    "model": "chatapp.message",
    "pk": 22,
    "fields": {
        "chat": 3,
        "author": 8,
        "content": "Donec id elit elementum, suscipit sem a, aliquam enim.",
        "timestamp": "2024-01-02T20:07:12.139Z"
    }
},
{
    "model": "chatapp.message",
    "pk": 23,
    "fields": {
        "chat": 5,
        "author": 7,
        "content": "Ut tempus sollicitudin velit id volutpat.",
        "timestamp": "2024-01-02T20:01:48.538Z"
    }
},
{
    "model": "chatapp.message",
    "pk": 24,
    "fields": {
        "chat": 5,
        "author": 7,
        "content": "Vivamus nec auctor risus.",
        "timestamp": "2024-01-02T20:02:05.714Z"
    }
},
{
    "model": "chatapp.message",
    "pk": 25,
    "fields": {
        "chat": 6,
        "author": 2,
        "content": "Sed sed elit ut nisi auctor lobortis et at metus. Fusce mattis orci libero, non placerat nisi efficitur sit amet. Integer scelerisque eros eu sollicitudin vehicula. Morbi maximus vulputate lectus, ac tincidunt augue tempor vel. Interdum et malesuada fames ac ante ipsum primis in faucibus.",
        "timestamp": "2024-01-02T20:02:22.651Z"
    }
},
{
    "model": "chatapp.message",
    "pk": 26,
    "fields": {
        "chat": 7,
        "author": 3,
        "content": "Fusce malesuada tempor lectus ut consectetur. Donec molestie consequat suscipit. Quisque non nisl id metus pellentesque facilisis ut nec nunc. In risus risus, fermentum non viverra id, egestas sit amet ex. Phasellus luctus urna sem, eu facilisis ipsum dapibus nec.",
        "timestamp": "2024-01-02T20:05:09.918Z"
    }
},
{
    "model": "chatapp.message",
    "pk": 27,
    "fields": {
        "chat": 7,
        "author":5,
        "content": "Nulla nec elit id ipsum bibendum blandit et non purus. Etiam augue sem, cursus eget suscipit ac, feugiat at elit. Fusce sed massa ut est pulvinar laoreet non eu enim. Pellentesque laoreet vestibulum sem eget bibendum. Aliquam id mauris non quam vehicula eleifend sed congue sem. Suspendisse sit amet justo ut ipsum congue varius in pretium nibh. Integer non bibendum dolor.",
        "timestamp": "2024-01-02T20:06:30.237Z"
    }
},
{
    "model": "chatapp.message",
    "pk": 28,
    "fields": {
        "chat": 7,
        "author": 3,
        "content": "Sed fringilla velit in dui pharetra commodo eu vel est. Suspendisse dignissim pharetra mi, vel venenatis erat tincidunt a.",
        "timestamp": "2024-01-02T20:06:49.957Z"
    }
},
{
    "model": "chatapp.message",
    "pk": 29,
    "fields": {
        "chat": 8,
        "author": 5,
        "content": "Donec id elit elementum, suscipit sem a, aliquam enim.",
        "timestamp": "2024-01-02T20:07:12.139Z"
    }
},
{
    "model": "chatapp.message",
    "pk": 30,
    "fields": {
        "chat": 8,
        "author": 3,
        "content": "Suspendisse commodo.",
        "timestamp": "2024-01-02T20:08:29.189Z"
    }
},
{
    "model": "chatapp.message",
    "pk": 31,
    "fields": {
        "chat": 8,
        "author": 5,
        "content": "Morbi vulputate ultricies orci, vel maximus turpis fermentum ut. Donec ut dignissim mi. Nunc eleifend tristique tortor, in pulvinar justo tempus quis. In hac habitasse platea dictumst. Sed eleifend in tortor a egestas.",
        "timestamp": "2024-01-02T20:09:04.988Z"
    }
},
{
    "model": "chatapp.message",
    "pk": 32,
    "fields": {
        "chat": 8,
        "author": 3,
        "content": "Vivamus in turpis in eros elementum maximus. Nullam facilisis faucibus augue, id sodales ante laoreet eu. Cras eu dapibus nisl, et ultrices neque.",
        "timestamp": "2024-01-02T20:09:19.296Z"
    }
},
{
    "model": "chatapp.message",
    "pk": 33,
    "fields": {
        "chat": 8,
        "author": 5,
        "content": "Aliquam vitae accumsan arcu. Nulla et metus id ligula aliquam fringilla. Sed tortor tellus, consequat id ornare tincidunt, malesuada sit amet nisl.",
        "timestamp": "2024-01-02T20:09:34.714Z"
    }
},
{
    "model": "chatapp.message",
    "pk": 34,
    "fields": {
        "chat": 8,
        "author": 3,
        "content": "Class aptent taciti sociosqu ad litora torquent per conubia nostra, per inceptos himenaeos.",
        "timestamp": "2024-01-06T07:09:19.296Z"
    }
},
{
    "model": "chatapp.message",
    "pk": 35,
    "fields": {
        "chat": 8,
        "author": 5,
        "content": "Duis semper hendrerit euismod.",
        "timestamp": "2024-01-06T09:09:34.714Z"
    }
},
{
    "model": "chatapp.message",
    "pk": 36,
    "fields": {
        "chat": 8,
        "author": 5,
        "content": "Vivamus volutpat malesuada sem, nec laoreet magna. Donec id erat tincidunt, euismod est malesuada, pellentesque nisi.",
        "timestamp": "2024-01-06T10:19:19.296Z"
    }
},
{
    "model": "chatapp.message",
    "pk": 37,
    "fields": {
        "chat": 9,
        "author": 8,
        "content": "Fusce luctus sodales pharetra.",
        "timestamp": "2024-01-06T10:20:34.714Z"
    }
}
]
